[
    {
        "end_at": "2025-07-05T21:55:00.000Z",
        "id": 34665498,
        "begin_at": "2025-07-05T15:11:22.000Z",
        "primary": true,
        "host": "c4r8p8",
        "campus_id": 21,
        "user": {
            "id": 189623,
            "email": "rabounou@student.1337.ma",
            "login": "rabounou",
            "first_name": "Radouane",
            "last_name": "Abounouas",
            "usual_full_name": "Radouane Abounouas",
            "usual_first_name": null,
            "url": "https://api.intra.42.fr/v2/users/rabounou",
            "phone": "hidden",
            "displayname": "Radouane Abounouas",
            "kind": "student",
            "image": {
                "link": "https://cdn.intra.42.fr/users/a2123fb1c38d394a7fb7d05c9271e159/rabounou.jpg",
                "versions": {
                    "large": "https://cdn.intra.42.fr/users/ac4f1baa948c4a6b8357415e22a36067/large_rabounou.jpg",
                    "medium": "https://cdn.intra.42.fr/users/684c9ac2ebde961baa64d229ce32e31a/medium_rabounou.jpg",
                    "small": "https://cdn.intra.42.fr/users/330d172100907f3bcdde67842d4dddcc/small_rabounou.jpg",
                    "micro": "https://cdn.intra.42.fr/users/2aab925e024d5aa1bf83b8cca9c3d280/micro_rabounou.jpg"
                }
            },
            "staff?": false,
            "correction_point": 5,
            "pool_month": "june",
            "pool_year": "2024",
            "location": "e1r13p1",
            "wallet": 40,
            "anonymize_date": "2028-07-06T00:00:00.000+01:00",
            "data_erasure_date": "2028-07-06T00:00:00.000+01:00",
            "created_at": "2024-06-21T09:59:35.635Z",
            "updated_at": "2025-07-05T20:55:37.992Z",
            "alumnized_at": null,
            "alumni?": false,
            "active?": true
        }
    },
    {
        "end_at": "2025-07-05T08:11:48.000Z",
        "id": 34657896,
        "begin_at": "2025-07-05T06:24:49.000Z",
        "primary": true,
        "host": "c4r8p7",
        "campus_id": 21,
        "user": {
            "id": 189623,
            "email": "rabounou@student.1337.ma",
            "login": "rabounou",
            "first_name": "Radouane",
            "last_name": "Abounouas",
            "usual_full_name": "Radouane Abounouas",
            "usual_first_name": null,
            "url": "https://api.intra.42.fr/v2/users/rabounou",
            "phone": "hidden",
            "displayname": "Radouane Abounouas",
            "kind": "student",
            "image": {
                "link": "https://cdn.intra.42.fr/users/a2123fb1c38d394a7fb7d05c9271e159/rabounou.jpg",
                "versions": {
                    "large": "https://cdn.intra.42.fr/users/ac4f1baa948c4a6b8357415e22a36067/large_rabounou.jpg",
                    "medium": "https://cdn.intra.42.fr/users/684c9ac2ebde961baa64d229ce32e31a/medium_rabounou.jpg",
                    "small": "https://cdn.intra.42.fr/users/330d172100907f3bcdde67842d4dddcc/small_rabounou.jpg",
                    "micro": "https://cdn.intra.42.fr/users/2aab925e024d5aa1bf83b8cca9c3d280/micro_rabounou.jpg"
                }
            },
            "staff?": false,
            "correction_point": 5,
            "pool_month": "june",
            "pool_year": "2024",
            "location": "e1r13p1",
            "wallet": 40,
            "anonymize_date": "2028-07-06T00:00:00.000+01:00",
            "data_erasure_date": "2028-07-06T00:00:00.000+01:00",
            "created_at": "2024-06-21T09:59:35.635Z",
            "updated_at": "2025-07-05T20:55:37.992Z",
            "alumnized_at": null,
            "alumni?": false,
            "active?": true
        }
    },
    {
        "end_at": "2025-07-05T06:15:53.000Z",
        "id": 34657405,
        "begin_at": "2025-07-05T02:46:20.000Z",
        "primary": true,
        "host": "c4r8p7",
        "campus_id": 21,
        "user": {
            "id": 189623,
            "email": "rabounou@student.1337.ma",
            "login": "rabounou",
            "first_name": "Radouane",
            "last_name": "Abounouas",
            "usual_full_name": "Radouane Abounouas",
            "usual_first_name": null,
            "url": "https://api.intra.42.fr/v2/users/rabounou",
            "phone": "hidden",
            "displayname": "Radouane Abounouas",
            "kind": "student",
            "image": {
                "link": "https://cdn.intra.42.fr/users/a2123fb1c38d394a7fb7d05c9271e159/rabounou.jpg",
                "versions": {
                    "large": "https://cdn.intra.42.fr/users/ac4f1baa948c4a6b8357415e22a36067/large_rabounou.jpg",
                    "medium": "https://cdn.intra.42.fr/users/684c9ac2ebde961baa64d229ce32e31a/medium_rabounou.jpg",
                    "small": "https://cdn.intra.42.fr/users/330d172100907f3bcdde67842d4dddcc/small_rabounou.jpg",
                    "micro": "https://cdn.intra.42.fr/users/2aab925e024d5aa1bf83b8cca9c3d280/micro_rabounou.jpg"
                }
            },
            "staff?": false,
            "correction_point": 5,
            "pool_month": "june",
            "pool_year": "2024",
            "location": "e1r13p1",
            "wallet": 40,
            "anonymize_date": "2028-07-06T00:00:00.000+01:00",
            "data_erasure_date": "2028-07-06T00:00:00.000+01:00",
            "created_at": "2024-06-21T09:59:35.635Z",
            "updated_at": "2025-07-05T20:55:37.992Z",
            "alumnized_at": null,
            "alumni?": false,
            "active?": true
        }
    },
    {
        "end_at": "2025-07-05T02:45:10.000Z",
        "id": 34656959,
        "begin_at": "2025-07-05T02:22:59.000Z",
        "primary": true,
        "host": "c4r8p9",
        "campus_id": 21,
        "user": {
            "id": 189623,
            "email": "rabounou@student.1337.ma",
            "login": "rabounou",
            "first_name": "Radouane",
            "last_name": "Abounouas",
            "usual_full_name": "Radouane Abounouas",
            "usual_first_name": null,
            "url": "https://api.intra.42.fr/v2/users/rabounou",
            "phone": "hidden",
            "displayname": "Radouane Abounouas",
            "kind": "student",
            "image": {
                "link": "https://cdn.intra.42.fr/users/a2123fb1c38d394a7fb7d05c9271e159/rabounou.jpg",
                "versions": {
                    "large": "https://cdn.intra.42.fr/users/ac4f1baa948c4a6b8357415e22a36067/large_rabounou.jpg",
                    "medium": "https://cdn.intra.42.fr/users/684c9ac2ebde961baa64d229ce32e31a/medium_rabounou.jpg",
                    "small": "https://cdn.intra.42.fr/users/330d172100907f3bcdde67842d4dddcc/small_rabounou.jpg",
                    "micro": "https://cdn.intra.42.fr/users/2aab925e024d5aa1bf83b8cca9c3d280/micro_rabounou.jpg"
                }
            },
            "staff?": false,
            "correction_point": 5,
            "pool_month": "june",
            "pool_year": "2024",
            "location": "e1r13p1",
            "wallet": 40,
            "anonymize_date": "2028-07-06T00:00:00.000+01:00",
            "data_erasure_date": "2028-07-06T00:00:00.000+01:00",
            "created_at": "2024-06-21T09:59:35.635Z",
            "updated_at": "2025-07-05T20:55:37.992Z",
            "alumnized_at": null,
            "alumni?": false,
            "active?": true
        }
    },
    {
        "end_at": "2025-07-05T01:39:13.000Z",
        "id": 34656816,
        "begin_at": "2025-07-04T22:39:18.000Z",
        "primary": true,
        "host": "c4r8p9",
        "campus_id": 21,
        "user": {
            "id": 189623,
            "email": "rabounou@student.1337.ma",
            "login": "rabounou",
            "first_name": "Radouane",
            "last_name": "Abounouas",
            "usual_full_name": "Radouane Abounouas",
            "usual_first_name": null,
            "url": "https://api.intra.42.fr/v2/users/rabounou",
            "phone": "hidden",
            "displayname": "Radouane Abounouas",
            "kind": "student",
            "image": {
                "link": "https://cdn.intra.42.fr/users/a2123fb1c38d394a7fb7d05c9271e159/rabounou.jpg",
                "versions": {
                    "large": "https://cdn.intra.42.fr/users/ac4f1baa948c4a6b8357415e22a36067/large_rabounou.jpg",
                    "medium": "https://cdn.intra.42.fr/users/684c9ac2ebde961baa64d229ce32e31a/medium_rabounou.jpg",
                    "small": "https://cdn.intra.42.fr/users/330d172100907f3bcdde67842d4dddcc/small_rabounou.jpg",
                    "micro": "https://cdn.intra.42.fr/users/2aab925e024d5aa1bf83b8cca9c3d280/micro_rabounou.jpg"
                }
            },
            "staff?": false,
            "correction_point": 5,
            "pool_month": "june",
            "pool_year": "2024",
            "location": "e1r13p1",
            "wallet": 40,
            "anonymize_date": "2028-07-06T00:00:00.000+01:00",
            "data_erasure_date": "2028-07-06T00:00:00.000+01:00",
            "created_at": "2024-06-21T09:59:35.635Z",
            "updated_at": "2025-07-05T20:55:37.992Z",
            "alumnized_at": null,
            "alumni?": false,
            "active?": true
        }
    },
    {
        "end_at": "2025-07-04T22:30:44.000Z",
        "id": 34656198,
        "begin_at": "2025-07-04T20:43:48.000Z",
        "primary": true,
        "host": "c4r8p9",
        "campus_id": 21,
        "user": {
            "id": 189623,
            "email": "rabounou@student.1337.ma",
            "login": "rabounou",
            "first_name": "Radouane",
            "last_name": "Abounouas",
            "usual_full_name": "Radouane Abounouas",
            "usual_first_name": null,
            "url": "https://api.intra.42.fr/v2/users/rabounou",
            "phone": "hidden",
            "displayname": "Radouane Abounouas",
            "kind": "student",
            "image": {
                "link": "https://cdn.intra.42.fr/users/a2123fb1c38d394a7fb7d05c9271e159/rabounou.jpg",
                "versions": {
                    "large": "https://cdn.intra.42.fr/users/ac4f1baa948c4a6b8357415e22a36067/large_rabounou.jpg",
                    "medium": "https://cdn.intra.42.fr/users/684c9ac2ebde961baa64d229ce32e31a/medium_rabounou.jpg",
                    "small": "https://cdn.intra.42.fr/users/330d172100907f3bcdde67842d4dddcc/small_rabounou.jpg",
                    "micro": "https://cdn.intra.42.fr/users/2aab925e024d5aa1bf83b8cca9c3d280/micro_rabounou.jpg"
                }
            },
            "staff?": false,
            "correction_point": 5,
            "pool_month": "june",
            "pool_year": "2024",
            "location": "e1r13p1",
            "wallet": 40,
            "anonymize_date": "2028-07-06T00:00:00.000+01:00",
            "data_erasure_date": "2028-07-06T00:00:00.000+01:00",
            "created_at": "2024-06-21T09:59:35.635Z",
            "updated_at": "2025-07-05T20:55:37.992Z",
            "alumnized_at": null,
            "alumni?": false,
            "active?": true
        }
    },
    {
        "end_at": "2025-07-04T20:31:55.000Z",
        "id": 34655349,
        "begin_at": "2025-07-04T14:22:06.000Z",
        "primary": true,
        "host": "c4r8p9",
        "campus_id": 21,
        "user": {
            "id": 189623,
            "email": "rabounou@student.1337.ma",
            "login": "rabounou",
            "first_name": "Radouane",
            "last_name": "Abounouas",
            "usual_full_name": "Radouane Abounouas",
            "usual_first_name": null,
            "url": "https://api.intra.42.fr/v2/users/rabounou",
            "phone": "hidden",
            "displayname": "Radouane Abounouas",
            "kind": "student",
            "image": {
                "link": "https://cdn.intra.42.fr/users/a2123fb1c38d394a7fb7d05c9271e159/rabounou.jpg",
                "versions": {
                    "large": "https://cdn.intra.42.fr/users/ac4f1baa948c4a6b8357415e22a36067/large_rabounou.jpg",
                    "medium": "https://cdn.intra.42.fr/users/684c9ac2ebde961baa64d229ce32e31a/medium_rabounou.jpg",
                    "small": "https://cdn.intra.42.fr/users/330d172100907f3bcdde67842d4dddcc/small_rabounou.jpg",
                    "micro": "https://cdn.intra.42.fr/users/2aab925e024d5aa1bf83b8cca9c3d280/micro_rabounou.jpg"
                }
            },
            "staff?": false,
            "correction_point": 5,
            "pool_month": "june",
            "pool_year": "2024",
            "location": "e1r13p1",
            "wallet": 40,
            "anonymize_date": "2028-07-06T00:00:00.000+01:00",
            "data_erasure_date": "2028-07-06T00:00:00.000+01:00",
            "created_at": "2024-06-21T09:59:35.635Z",
            "updated_at": "2025-07-05T20:55:37.992Z",
            "alumnized_at": null,
            "alumni?": false,
            "active?": true
        }
    },
    {
        "end_at": "2025-07-03T19:07:55.000Z",
        "id": 34640626,
        "begin_at": "2025-07-03T15:13:35.000Z",
        "primary": true,
        "host": "c4r8p9",
        "campus_id": 21,
        "user": {
            "id": 189623,
            "email": "rabounou@student.1337.ma",
            "login": "rabounou",
            "first_name": "Radouane",
            "last_name": "Abounouas",
            "usual_full_name": "Radouane Abounouas",
            "usual_first_name": null,
            "url": "https://api.intra.42.fr/v2/users/rabounou",
            "phone": "hidden",
            "displayname": "Radouane Abounouas",
            "kind": "student",
            "image": {
                "link": "https://cdn.intra.42.fr/users/a2123fb1c38d394a7fb7d05c9271e159/rabounou.jpg",
                "versions": {
                    "large": "https://cdn.intra.42.fr/users/ac4f1baa948c4a6b8357415e22a36067/large_rabounou.jpg",
                    "medium": "https://cdn.intra.42.fr/users/684c9ac2ebde961baa64d229ce32e31a/medium_rabounou.jpg",
                    "small": "https://cdn.intra.42.fr/users/330d172100907f3bcdde67842d4dddcc/small_rabounou.jpg",
                    "micro": "https://cdn.intra.42.fr/users/2aab925e024d5aa1bf83b8cca9c3d280/micro_rabounou.jpg"
                }
            },
            "staff?": false,
            "correction_point": 5,
            "pool_month": "june",
            "pool_year": "2024",
            "location": "e1r13p1",
            "wallet": 40,
            "anonymize_date": "2028-07-06T00:00:00.000+01:00",
            "data_erasure_date": "2028-07-06T00:00:00.000+01:00",
            "created_at": "2024-06-21T09:59:35.635Z",
            "updated_at": "2025-07-05T20:55:37.992Z",
            "alumnized_at": null,
            "alumni?": false,
            "active?": true
        }
    },
    {
        "end_at": "2025-07-03T15:04:29.000Z",
        "id": 34637055,
        "begin_at": "2025-07-03T13:34:59.000Z",
        "primary": true,
        "host": "c4r8p9",
        "campus_id": 21,
        "user": {
            "id": 189623,
            "email": "rabounou@student.1337.ma",
            "login": "rabounou",
            "first_name": "Radouane",
            "last_name": "Abounouas",
            "usual_full_name": "Radouane Abounouas",
            "usual_first_name": null,
            "url": "https://api.intra.42.fr/v2/users/rabounou",
            "phone": "hidden",
            "displayname": "Radouane Abounouas",
            "kind": "student",
            "image": {
                "link": "https://cdn.intra.42.fr/users/a2123fb1c38d394a7fb7d05c9271e159/rabounou.jpg",
                "versions": {
                    "large": "https://cdn.intra.42.fr/users/ac4f1baa948c4a6b8357415e22a36067/large_rabounou.jpg",
                    "medium": "https://cdn.intra.42.fr/users/684c9ac2ebde961baa64d229ce32e31a/medium_rabounou.jpg",
                    "small": "https://cdn.intra.42.fr/users/330d172100907f3bcdde67842d4dddcc/small_rabounou.jpg",
                    "micro": "https://cdn.intra.42.fr/users/2aab925e024d5aa1bf83b8cca9c3d280/micro_rabounou.jpg"
                }
            },
            "staff?": false,
            "correction_point": 5,
            "pool_month": "june",
            "pool_year": "2024",
            "location": "e1r13p1",
            "wallet": 40,
            "anonymize_date": "2028-07-06T00:00:00.000+01:00",
            "data_erasure_date": "2028-07-06T00:00:00.000+01:00",
            "created_at": "2024-06-21T09:59:35.635Z",
            "updated_at": "2025-07-05T20:55:37.992Z",
            "alumnized_at": null,
            "alumni?": false,
            "active?": true
        }
    },
    {
        "end_at": "2025-07-03T01:32:29.000Z",
        "id": 34627267,
        "begin_at": "2025-07-02T18:35:05.000Z",
        "primary": true,
        "host": "c4r8p9",
        "campus_id": 21,
        "user": {
            "id": 189623,
            "email": "rabounou@student.1337.ma",
            "login": "rabounou",
            "first_name": "Radouane",
            "last_name": "Abounouas",
            "usual_full_name": "Radouane Abounouas",
            "usual_first_name": null,
            "url": "https://api.intra.42.fr/v2/users/rabounou",
            "phone": "hidden",
            "displayname": "Radouane Abounouas",
            "kind": "student",
            "image": {
                "link": "https://cdn.intra.42.fr/users/a2123fb1c38d394a7fb7d05c9271e159/rabounou.jpg",
                "versions": {
                    "large": "https://cdn.intra.42.fr/users/ac4f1baa948c4a6b8357415e22a36067/large_rabounou.jpg",
                    "medium": "https://cdn.intra.42.fr/users/684c9ac2ebde961baa64d229ce32e31a/medium_rabounou.jpg",
                    "small": "https://cdn.intra.42.fr/users/330d172100907f3bcdde67842d4dddcc/small_rabounou.jpg",
                    "micro": "https://cdn.intra.42.fr/users/2aab925e024d5aa1bf83b8cca9c3d280/micro_rabounou.jpg"
                }
            },
            "staff?": false,
            "correction_point": 5,
            "pool_month": "june",
            "pool_year": "2024",
            "location": "e1r13p1",
            "wallet": 40,
            "anonymize_date": "2028-07-06T00:00:00.000+01:00",
            "data_erasure_date": "2028-07-06T00:00:00.000+01:00",
            "created_at": "2024-06-21T09:59:35.635Z",
            "updated_at": "2025-07-05T20:55:37.992Z",
            "alumnized_at": null,
            "alumni?": false,
            "active?": true
        }
    },
    {
        "end_at": "2025-07-02T16:32:29.000Z",
        "id": 34622538,
        "begin_at": "2025-07-02T16:13:17.000Z",
        "primary": false,
        "host": "c3r3p4",
        "campus_id": 21,
        "user": {
            "id": 189623,
            "email": "rabounou@student.1337.ma",
            "login": "rabounou",
            "first_name": "Radouane",
            "last_name": "Abounouas",
            "usual_full_name": "Radouane Abounouas",
            "usual_first_name": null,
            "url": "https://api.intra.42.fr/v2/users/rabounou",
            "phone": "hidden",
            "displayname": "Radouane Abounouas",
            "kind": "student",
            "image": {
                "link": "https://cdn.intra.42.fr/users/a2123fb1c38d394a7fb7d05c9271e159/rabounou.jpg",
                "versions": {
                    "large": "https://cdn.intra.42.fr/users/ac4f1baa948c4a6b8357415e22a36067/large_rabounou.jpg",
                    "medium": "https://cdn.intra.42.fr/users/684c9ac2ebde961baa64d229ce32e31a/medium_rabounou.jpg",
                    "small": "https://cdn.intra.42.fr/users/330d172100907f3bcdde67842d4dddcc/small_rabounou.jpg",
                    "micro": "https://cdn.intra.42.fr/users/2aab925e024d5aa1bf83b8cca9c3d280/micro_rabounou.jpg"
                }
            },
            "staff?": false,
            "correction_point": 5,
            "pool_month": "june",
            "pool_year": "2024",
            "location": "e1r13p1",
            "wallet": 40,
            "anonymize_date": "2028-07-06T00:00:00.000+01:00",
            "data_erasure_date": "2028-07-06T00:00:00.000+01:00",
            "created_at": "2024-06-21T09:59:35.635Z",
            "updated_at": "2025-07-05T20:55:37.992Z",
            "alumnized_at": null,
            "alumni?": false,
            "active?": true
        }
    },
    {
        "end_at": "2025-07-02T15:05:00.000Z",
        "id": 34621049,
        "begin_at": "2025-07-02T14:54:46.000Z",
        "primary": false,
        "host": "c3r5p6",
        "campus_id": 21,
        "user": {
            "id": 189623,
            "email": "rabounou@student.1337.ma",
            "login": "rabounou",
            "first_name": "Radouane",
            "last_name": "Abounouas",
            "usual_full_name": "Radouane Abounouas",
            "usual_first_name": null,
            "url": "https://api.intra.42.fr/v2/users/rabounou",
            "phone": "hidden",
            "displayname": "Radouane Abounouas",
            "kind": "student",
            "image": {
                "link": "https://cdn.intra.42.fr/users/a2123fb1c38d394a7fb7d05c9271e159/rabounou.jpg",
                "versions": {
                    "large": "https://cdn.intra.42.fr/users/ac4f1baa948c4a6b8357415e22a36067/large_rabounou.jpg",
                    "medium": "https://cdn.intra.42.fr/users/684c9ac2ebde961baa64d229ce32e31a/medium_rabounou.jpg",
                    "small": "https://cdn.intra.42.fr/users/330d172100907f3bcdde67842d4dddcc/small_rabounou.jpg",
                    "micro": "https://cdn.intra.42.fr/users/2aab925e024d5aa1bf83b8cca9c3d280/micro_rabounou.jpg"
                }
            },
            "staff?": false,
            "correction_point": 5,
            "pool_month": "june",
            "pool_year": "2024",
            "location": "e1r13p1",
            "wallet": 40,
            "anonymize_date": "2028-07-06T00:00:00.000+01:00",
            "data_erasure_date": "2028-07-06T00:00:00.000+01:00",
            "created_at": "2024-06-21T09:59:35.635Z",
            "updated_at": "2025-07-05T20:55:37.992Z",
            "alumnized_at": null,
            "alumni?": false,
            "active?": true
        }
    },
    {
        "end_at": "2025-07-02T14:46:21.000Z",
        "id": 34620831,
        "begin_at": "2025-07-02T14:06:18.000Z",
        "primary": true,
        "host": "c4r8p9",
        "campus_id": 21,
        "user": {
            "id": 189623,
            "email": "rabounou@student.1337.ma",
            "login": "rabounou",
            "first_name": "Radouane",
            "last_name": "Abounouas",
            "usual_full_name": "Radouane Abounouas",
            "usual_first_name": null,
            "url": "https://api.intra.42.fr/v2/users/rabounou",
            "phone": "hidden",
            "displayname": "Radouane Abounouas",
            "kind": "student",
            "image": {
                "link": "https://cdn.intra.42.fr/users/a2123fb1c38d394a7fb7d05c9271e159/rabounou.jpg",
                "versions": {
                    "large": "https://cdn.intra.42.fr/users/ac4f1baa948c4a6b8357415e22a36067/large_rabounou.jpg",
                    "medium": "https://cdn.intra.42.fr/users/684c9ac2ebde961baa64d229ce32e31a/medium_rabounou.jpg",
                    "small": "https://cdn.intra.42.fr/users/330d172100907f3bcdde67842d4dddcc/small_rabounou.jpg",
                    "micro": "https://cdn.intra.42.fr/users/2aab925e024d5aa1bf83b8cca9c3d280/micro_rabounou.jpg"
                }
            },
            "staff?": false,
            "correction_point": 5,
            "pool_month": "june",
            "pool_year": "2024",
            "location": "e1r13p1",
            "wallet": 40,
            "anonymize_date": "2028-07-06T00:00:00.000+01:00",
            "data_erasure_date": "2028-07-06T00:00:00.000+01:00",
            "created_at": "2024-06-21T09:59:35.635Z",
            "updated_at": "2025-07-05T20:55:37.992Z",
            "alumnized_at": null,
            "alumni?": false,
            "active?": true
        }
    },
    {
        "end_at": "2025-07-02T00:36:33.000Z",
        "id": 34611377,
        "begin_at": "2025-07-01T22:21:09.000Z",
        "primary": true,
        "host": "c4r8p9",
        "campus_id": 21,
        "user": {
            "id": 189623,
            "email": "rabounou@student.1337.ma",
            "login": "rabounou",
            "first_name": "Radouane",
            "last_name": "Abounouas",
            "usual_full_name": "Radouane Abounouas",
            "usual_first_name": null,
            "url": "https://api.intra.42.fr/v2/users/rabounou",
            "phone": "hidden",
            "displayname": "Radouane Abounouas",
            "kind": "student",
            "image": {
                "link": "https://cdn.intra.42.fr/users/a2123fb1c38d394a7fb7d05c9271e159/rabounou.jpg",
                "versions": {
                    "large": "https://cdn.intra.42.fr/users/ac4f1baa948c4a6b8357415e22a36067/large_rabounou.jpg",
                    "medium": "https://cdn.intra.42.fr/users/684c9ac2ebde961baa64d229ce32e31a/medium_rabounou.jpg",
                    "small": "https://cdn.intra.42.fr/users/330d172100907f3bcdde67842d4dddcc/small_rabounou.jpg",
                    "micro": "https://cdn.intra.42.fr/users/2aab925e024d5aa1bf83b8cca9c3d280/micro_rabounou.jpg"
                }
            },
            "staff?": false,
            "correction_point": 5,
            "pool_month": "june",
            "pool_year": "2024",
            "location": "e1r13p1",
            "wallet": 40,
            "anonymize_date": "2028-07-06T00:00:00.000+01:00",
            "data_erasure_date": "2028-07-06T00:00:00.000+01:00",
            "created_at": "2024-06-21T09:59:35.635Z",
            "updated_at": "2025-07-05T20:55:37.992Z",
            "alumnized_at": null,
            "alumni?": false,
            "active?": true
        }
    },
    {
        "end_at": "2025-07-01T20:38:52.000Z",
        "id": 34610068,
        "begin_at": "2025-07-01T17:45:11.000Z",
        "primary": true,
        "host": "c4r8p9",
        "campus_id": 21,
        "user": {
            "id": 189623,
            "email": "rabounou@student.1337.ma",
            "login": "rabounou",
            "first_name": "Radouane",
            "last_name": "Abounouas",
            "usual_full_name": "Radouane Abounouas",
            "usual_first_name": null,
            "url": "https://api.intra.42.fr/v2/users/rabounou",
            "phone": "hidden",
            "displayname": "Radouane Abounouas",
            "kind": "student",
            "image": {
                "link": "https://cdn.intra.42.fr/users/a2123fb1c38d394a7fb7d05c9271e159/rabounou.jpg",
                "versions": {
                    "large": "https://cdn.intra.42.fr/users/ac4f1baa948c4a6b8357415e22a36067/large_rabounou.jpg",
                    "medium": "https://cdn.intra.42.fr/users/684c9ac2ebde961baa64d229ce32e31a/medium_rabounou.jpg",
                    "small": "https://cdn.intra.42.fr/users/330d172100907f3bcdde67842d4dddcc/small_rabounou.jpg",
                    "micro": "https://cdn.intra.42.fr/users/2aab925e024d5aa1bf83b8cca9c3d280/micro_rabounou.jpg"
                }
            },
            "staff?": false,
            "correction_point": 5,
            "pool_month": "june",
            "pool_year": "2024",
            "location": "e1r13p1",
            "wallet": 40,
            "anonymize_date": "2028-07-06T00:00:00.000+01:00",
            "data_erasure_date": "2028-07-06T00:00:00.000+01:00",
            "created_at": "2024-06-21T09:59:35.635Z",
            "updated_at": "2025-07-05T20:55:37.992Z",
            "alumnized_at": null,
            "alumni?": false,
            "active?": true
        }
    },
    {
        "end_at": "2025-07-01T17:36:01.000Z",
        "id": 34607920,
        "begin_at": "2025-07-01T13:58:14.000Z",
        "primary": true,
        "host": "c4r8p9",
        "campus_id": 21,
        "user": {
            "id": 189623,
            "email": "rabounou@student.1337.ma",
            "login": "rabounou",
            "first_name": "Radouane",
            "last_name": "Abounouas",
            "usual_full_name": "Radouane Abounouas",
            "usual_first_name": null,
            "url": "https://api.intra.42.fr/v2/users/rabounou",
            "phone": "hidden",
            "displayname": "Radouane Abounouas",
            "kind": "student",
            "image": {
                "link": "https://cdn.intra.42.fr/users/a2123fb1c38d394a7fb7d05c9271e159/rabounou.jpg",
                "versions": {
                    "large": "https://cdn.intra.42.fr/users/ac4f1baa948c4a6b8357415e22a36067/large_rabounou.jpg",
                    "medium": "https://cdn.intra.42.fr/users/684c9ac2ebde961baa64d229ce32e31a/medium_rabounou.jpg",
                    "small": "https://cdn.intra.42.fr/users/330d172100907f3bcdde67842d4dddcc/small_rabounou.jpg",
                    "micro": "https://cdn.intra.42.fr/users/2aab925e024d5aa1bf83b8cca9c3d280/micro_rabounou.jpg"
                }
            },
            "staff?": false,
            "correction_point": 5,
            "pool_month": "june",
            "pool_year": "2024",
            "location": "e1r13p1",
            "wallet": 40,
            "anonymize_date": "2028-07-06T00:00:00.000+01:00",
            "data_erasure_date": "2028-07-06T00:00:00.000+01:00",
            "created_at": "2024-06-21T09:59:35.635Z",
            "updated_at": "2025-07-05T20:55:37.992Z",
            "alumnized_at": null,
            "alumni?": false,
            "active?": true
        }
    },
    {
        "end_at": "2025-06-30T23:47:24.000Z",
        "id": 34595033,
        "begin_at": "2025-06-30T21:06:12.000Z",
        "primary": true,
        "host": "c4r8p9",
        "campus_id": 21,
        "user": {
            "id": 189623,
            "email": "rabounou@student.1337.ma",
            "login": "rabounou",
            "first_name": "Radouane",
            "last_name": "Abounouas",
            "usual_full_name": "Radouane Abounouas",
            "usual_first_name": null,
            "url": "https://api.intra.42.fr/v2/users/rabounou",
            "phone": "hidden",
            "displayname": "Radouane Abounouas",
            "kind": "student",
            "image": {
                "link": "https://cdn.intra.42.fr/users/a2123fb1c38d394a7fb7d05c9271e159/rabounou.jpg",
                "versions": {
                    "large": "https://cdn.intra.42.fr/users/ac4f1baa948c4a6b8357415e22a36067/large_rabounou.jpg",
                    "medium": "https://cdn.intra.42.fr/users/684c9ac2ebde961baa64d229ce32e31a/medium_rabounou.jpg",
                    "small": "https://cdn.intra.42.fr/users/330d172100907f3bcdde67842d4dddcc/small_rabounou.jpg",
                    "micro": "https://cdn.intra.42.fr/users/2aab925e024d5aa1bf83b8cca9c3d280/micro_rabounou.jpg"
                }
            },
            "staff?": false,
            "correction_point": 5,
            "pool_month": "june",
            "pool_year": "2024",
            "location": "e1r13p1",
            "wallet": 40,
            "anonymize_date": "2028-07-06T00:00:00.000+01:00",
            "data_erasure_date": "2028-07-06T00:00:00.000+01:00",
            "created_at": "2024-06-21T09:59:35.635Z",
            "updated_at": "2025-07-05T20:55:37.992Z",
            "alumnized_at": null,
            "alumni?": false,
            "active?": true
        }
    },
    {
        "end_at": "2025-06-30T20:03:01.000Z",
        "id": 34593824,
        "begin_at": "2025-06-30T18:50:25.000Z",
        "primary": true,
        "host": "c4r8p9",
        "campus_id": 21,
        "user": {
            "id": 189623,
            "email": "rabounou@student.1337.ma",
            "login": "rabounou",
            "first_name": "Radouane",
            "last_name": "Abounouas",
            "usual_full_name": "Radouane Abounouas",
            "usual_first_name": null,
            "url": "https://api.intra.42.fr/v2/users/rabounou",
            "phone": "hidden",
            "displayname": "Radouane Abounouas",
            "kind": "student",
            "image": {
                "link": "https://cdn.intra.42.fr/users/a2123fb1c38d394a7fb7d05c9271e159/rabounou.jpg",
                "versions": {
                    "large": "https://cdn.intra.42.fr/users/ac4f1baa948c4a6b8357415e22a36067/large_rabounou.jpg",
                    "medium": "https://cdn.intra.42.fr/users/684c9ac2ebde961baa64d229ce32e31a/medium_rabounou.jpg",
                    "small": "https://cdn.intra.42.fr/users/330d172100907f3bcdde67842d4dddcc/small_rabounou.jpg",
                    "micro": "https://cdn.intra.42.fr/users/2aab925e024d5aa1bf83b8cca9c3d280/micro_rabounou.jpg"
                }
            },
            "staff?": false,
            "correction_point": 5,
            "pool_month": "june",
            "pool_year": "2024",
            "location": "e1r13p1",
            "wallet": 40,
            "anonymize_date": "2028-07-06T00:00:00.000+01:00",
            "data_erasure_date": "2028-07-06T00:00:00.000+01:00",
            "created_at": "2024-06-21T09:59:35.635Z",
            "updated_at": "2025-07-05T20:55:37.992Z",
            "alumnized_at": null,
            "alumni?": false,
            "active?": true
        }
    },
    {
        "end_at": "2025-06-30T15:47:04.000Z",
        "id": 34591064,
        "begin_at": "2025-06-30T14:55:05.000Z",
        "primary": true,
        "host": "c4r8p7",
        "campus_id": 21,
        "user": {
            "id": 189623,
            "email": "rabounou@student.1337.ma",
            "login": "rabounou",
            "first_name": "Radouane",
            "last_name": "Abounouas",
            "usual_full_name": "Radouane Abounouas",
            "usual_first_name": null,
            "url": "https://api.intra.42.fr/v2/users/rabounou",
            "phone": "hidden",
            "displayname": "Radouane Abounouas",
            "kind": "student",
            "image": {
                "link": "https://cdn.intra.42.fr/users/a2123fb1c38d394a7fb7d05c9271e159/rabounou.jpg",
                "versions": {
                    "large": "https://cdn.intra.42.fr/users/ac4f1baa948c4a6b8357415e22a36067/large_rabounou.jpg",
                    "medium": "https://cdn.intra.42.fr/users/684c9ac2ebde961baa64d229ce32e31a/medium_rabounou.jpg",
                    "small": "https://cdn.intra.42.fr/users/330d172100907f3bcdde67842d4dddcc/small_rabounou.jpg",
                    "micro": "https://cdn.intra.42.fr/users/2aab925e024d5aa1bf83b8cca9c3d280/micro_rabounou.jpg"
                }
            },
            "staff?": false,
            "correction_point": 5,
            "pool_month": "june",
            "pool_year": "2024",
            "location": "e1r13p1",
            "wallet": 40,
            "anonymize_date": "2028-07-06T00:00:00.000+01:00",
            "data_erasure_date": "2028-07-06T00:00:00.000+01:00",
            "created_at": "2024-06-21T09:59:35.635Z",
            "updated_at": "2025-07-05T20:55:37.992Z",
            "alumnized_at": null,
            "alumni?": false,
            "active?": true
        }
    },
    {
        "end_at": "2025-06-30T11:49:13.000Z",
        "id": 34585923,
        "begin_at": "2025-06-30T09:29:32.000Z",
        "primary": true,
        "host": "c4r8p9",
        "campus_id": 21,
        "user": {
            "id": 189623,
            "email": "rabounou@student.1337.ma",
            "login": "rabounou",
            "first_name": "Radouane",
            "last_name": "Abounouas",
            "usual_full_name": "Radouane Abounouas",
            "usual_first_name": null,
            "url": "https://api.intra.42.fr/v2/users/rabounou",
            "phone": "hidden",
            "displayname": "Radouane Abounouas",
            "kind": "student",
            "image": {
                "link": "https://cdn.intra.42.fr/users/a2123fb1c38d394a7fb7d05c9271e159/rabounou.jpg",
                "versions": {
                    "large": "https://cdn.intra.42.fr/users/ac4f1baa948c4a6b8357415e22a36067/large_rabounou.jpg",
                    "medium": "https://cdn.intra.42.fr/users/684c9ac2ebde961baa64d229ce32e31a/medium_rabounou.jpg",
                    "small": "https://cdn.intra.42.fr/users/330d172100907f3bcdde67842d4dddcc/small_rabounou.jpg",
                    "micro": "https://cdn.intra.42.fr/users/2aab925e024d5aa1bf83b8cca9c3d280/micro_rabounou.jpg"
                }
            },
            "staff?": false,
            "correction_point": 5,
            "pool_month": "june",
            "pool_year": "2024",
            "location": "e1r13p1",
            "wallet": 40,
            "anonymize_date": "2028-07-06T00:00:00.000+01:00",
            "data_erasure_date": "2028-07-06T00:00:00.000+01:00",
            "created_at": "2024-06-21T09:59:35.635Z",
            "updated_at": "2025-07-05T20:55:37.992Z",
            "alumnized_at": null,
            "alumni?": false,
            "active?": true
        }
    },
    {
        "end_at": "2025-06-29T22:59:05.000Z",
        "id": 34579477,
        "begin_at": "2025-06-29T21:42:31.000Z",
        "primary": false,
        "host": "c4r9p6",
        "campus_id": 21,
        "user": {
            "id": 189623,
            "email": "rabounou@student.1337.ma",
            "login": "rabounou",
            "first_name": "Radouane",
            "last_name": "Abounouas",
            "usual_full_name": "Radouane Abounouas",
            "usual_first_name": null,
            "url": "https://api.intra.42.fr/v2/users/rabounou",
            "phone": "hidden",
            "displayname": "Radouane Abounouas",
            "kind": "student",
            "image": {
                "link": "https://cdn.intra.42.fr/users/a2123fb1c38d394a7fb7d05c9271e159/rabounou.jpg",
                "versions": {
                    "large": "https://cdn.intra.42.fr/users/ac4f1baa948c4a6b8357415e22a36067/large_rabounou.jpg",
                    "medium": "https://cdn.intra.42.fr/users/684c9ac2ebde961baa64d229ce32e31a/medium_rabounou.jpg",
                    "small": "https://cdn.intra.42.fr/users/330d172100907f3bcdde67842d4dddcc/small_rabounou.jpg",
                    "micro": "https://cdn.intra.42.fr/users/2aab925e024d5aa1bf83b8cca9c3d280/micro_rabounou.jpg"
                }
            },
            "staff?": false,
            "correction_point": 5,
            "pool_month": "june",
            "pool_year": "2024",
            "location": "e1r13p1",
            "wallet": 40,
            "anonymize_date": "2028-07-06T00:00:00.000+01:00",
            "data_erasure_date": "2028-07-06T00:00:00.000+01:00",
            "created_at": "2024-06-21T09:59:35.635Z",
            "updated_at": "2025-07-05T20:55:37.992Z",
            "alumnized_at": null,
            "alumni?": false,
            "active?": true
        }
    },
    {
        "end_at": "2025-06-29T21:32:31.000Z",
        "id": 34575921,
        "begin_at": "2025-06-29T14:21:08.000Z",
        "primary": false,
        "host": "c4r9p6",
        "campus_id": 21,
        "user": {
            "id": 189623,
            "email": "rabounou@student.1337.ma",
            "login": "rabounou",
            "first_name": "Radouane",
            "last_name": "Abounouas",
            "usual_full_name": "Radouane Abounouas",
            "usual_first_name": null,
            "url": "https://api.intra.42.fr/v2/users/rabounou",
            "phone": "hidden",
            "displayname": "Radouane Abounouas",
            "kind": "student",
            "image": {
                "link": "https://cdn.intra.42.fr/users/a2123fb1c38d394a7fb7d05c9271e159/rabounou.jpg",
                "versions": {
                    "large": "https://cdn.intra.42.fr/users/ac4f1baa948c4a6b8357415e22a36067/large_rabounou.jpg",
                    "medium": "https://cdn.intra.42.fr/users/684c9ac2ebde961baa64d229ce32e31a/medium_rabounou.jpg",
                    "small": "https://cdn.intra.42.fr/users/330d172100907f3bcdde67842d4dddcc/small_rabounou.jpg",
                    "micro": "https://cdn.intra.42.fr/users/2aab925e024d5aa1bf83b8cca9c3d280/micro_rabounou.jpg"
                }
            },
            "staff?": false,
            "correction_point": 5,
            "pool_month": "june",
            "pool_year": "2024",
            "location": "e1r13p1",
            "wallet": 40,
            "anonymize_date": "2028-07-06T00:00:00.000+01:00",
            "data_erasure_date": "2028-07-06T00:00:00.000+01:00",
            "created_at": "2024-06-21T09:59:35.635Z",
            "updated_at": "2025-07-05T20:55:37.992Z",
            "alumnized_at": null,
            "alumni?": false,
            "active?": true
        }
    },
    {
        "end_at": "2025-06-29T01:30:32.000Z",
        "id": 34572001,
        "begin_at": "2025-06-28T14:17:22.000Z",
        "primary": true,
        "host": "c4r8p9",
        "campus_id": 21,
        "user": {
            "id": 189623,
            "email": "rabounou@student.1337.ma",
            "login": "rabounou",
            "first_name": "Radouane",
            "last_name": "Abounouas",
            "usual_full_name": "Radouane Abounouas",
            "usual_first_name": null,
            "url": "https://api.intra.42.fr/v2/users/rabounou",
            "phone": "hidden",
            "displayname": "Radouane Abounouas",
            "kind": "student",
            "image": {
                "link": "https://cdn.intra.42.fr/users/a2123fb1c38d394a7fb7d05c9271e159/rabounou.jpg",
                "versions": {
                    "large": "https://cdn.intra.42.fr/users/ac4f1baa948c4a6b8357415e22a36067/large_rabounou.jpg",
                    "medium": "https://cdn.intra.42.fr/users/684c9ac2ebde961baa64d229ce32e31a/medium_rabounou.jpg",
                    "small": "https://cdn.intra.42.fr/users/330d172100907f3bcdde67842d4dddcc/small_rabounou.jpg",
                    "micro": "https://cdn.intra.42.fr/users/2aab925e024d5aa1bf83b8cca9c3d280/micro_rabounou.jpg"
                }
            },
            "staff?": false,
            "correction_point": 5,
            "pool_month": "june",
            "pool_year": "2024",
            "location": "e1r13p1",
            "wallet": 40,
            "anonymize_date": "2028-07-06T00:00:00.000+01:00",
            "data_erasure_date": "2028-07-06T00:00:00.000+01:00",
            "created_at": "2024-06-21T09:59:35.635Z",
            "updated_at": "2025-07-05T20:55:37.992Z",
            "alumnized_at": null,
            "alumni?": false,
            "active?": true
        }
    },
    {
        "end_at": "2025-06-27T23:41:02.000Z",
        "id": 34562638,
        "begin_at": "2025-06-27T21:11:34.000Z",
        "primary": true,
        "host": "c4r8p8",
        "campus_id": 21,
        "user": {
            "id": 189623,
            "email": "rabounou@student.1337.ma",
            "login": "rabounou",
            "first_name": "Radouane",
            "last_name": "Abounouas",
            "usual_full_name": "Radouane Abounouas",
            "usual_first_name": null,
            "url": "https://api.intra.42.fr/v2/users/rabounou",
            "phone": "hidden",
            "displayname": "Radouane Abounouas",
            "kind": "student",
            "image": {
                "link": "https://cdn.intra.42.fr/users/a2123fb1c38d394a7fb7d05c9271e159/rabounou.jpg",
                "versions": {
                    "large": "https://cdn.intra.42.fr/users/ac4f1baa948c4a6b8357415e22a36067/large_rabounou.jpg",
                    "medium": "https://cdn.intra.42.fr/users/684c9ac2ebde961baa64d229ce32e31a/medium_rabounou.jpg",
                    "small": "https://cdn.intra.42.fr/users/330d172100907f3bcdde67842d4dddcc/small_rabounou.jpg",
                    "micro": "https://cdn.intra.42.fr/users/2aab925e024d5aa1bf83b8cca9c3d280/micro_rabounou.jpg"
                }
            },
            "staff?": false,
            "correction_point": 5,
            "pool_month": "june",
            "pool_year": "2024",
            "location": "e1r13p1",
            "wallet": 40,
            "anonymize_date": "2028-07-06T00:00:00.000+01:00",
            "data_erasure_date": "2028-07-06T00:00:00.000+01:00",
            "created_at": "2024-06-21T09:59:35.635Z",
            "updated_at": "2025-07-05T20:55:37.992Z",
            "alumnized_at": null,
            "alumni?": false,
            "active?": true
        }
    },
    {
        "end_at": "2025-06-27T16:43:19.000Z",
        "id": 34559499,
        "begin_at": "2025-06-27T10:26:24.000Z",
        "primary": true,
        "host": "c4r8p8",
        "campus_id": 21,
        "user": {
            "id": 189623,
            "email": "rabounou@student.1337.ma",
            "login": "rabounou",
            "first_name": "Radouane",
            "last_name": "Abounouas",
            "usual_full_name": "Radouane Abounouas",
            "usual_first_name": null,
            "url": "https://api.intra.42.fr/v2/users/rabounou",
            "phone": "hidden",
            "displayname": "Radouane Abounouas",
            "kind": "student",
            "image": {
                "link": "https://cdn.intra.42.fr/users/a2123fb1c38d394a7fb7d05c9271e159/rabounou.jpg",
                "versions": {
                    "large": "https://cdn.intra.42.fr/users/ac4f1baa948c4a6b8357415e22a36067/large_rabounou.jpg",
                    "medium": "https://cdn.intra.42.fr/users/684c9ac2ebde961baa64d229ce32e31a/medium_rabounou.jpg",
                    "small": "https://cdn.intra.42.fr/users/330d172100907f3bcdde67842d4dddcc/small_rabounou.jpg",
                    "micro": "https://cdn.intra.42.fr/users/2aab925e024d5aa1bf83b8cca9c3d280/micro_rabounou.jpg"
                }
            },
            "staff?": false,
            "correction_point": 5,
            "pool_month": "june",
            "pool_year": "2024",
            "location": "e1r13p1",
            "wallet": 40,
            "anonymize_date": "2028-07-06T00:00:00.000+01:00",
            "data_erasure_date": "2028-07-06T00:00:00.000+01:00",
            "created_at": "2024-06-21T09:59:35.635Z",
            "updated_at": "2025-07-05T20:55:37.992Z",
            "alumnized_at": null,
            "alumni?": false,
            "active?": true
        }
    },
    {
        "end_at": "2025-06-27T10:24:50.000Z",
        "id": 34553173,
        "begin_at": "2025-06-27T10:12:15.000Z",
        "primary": true,
        "host": "c4r8p8",
        "campus_id": 21,
        "user": {
            "id": 189623,
            "email": "rabounou@student.1337.ma",
            "login": "rabounou",
            "first_name": "Radouane",
            "last_name": "Abounouas",
            "usual_full_name": "Radouane Abounouas",
            "usual_first_name": null,
            "url": "https://api.intra.42.fr/v2/users/rabounou",
            "phone": "hidden",
            "displayname": "Radouane Abounouas",
            "kind": "student",
            "image": {
                "link": "https://cdn.intra.42.fr/users/a2123fb1c38d394a7fb7d05c9271e159/rabounou.jpg",
                "versions": {
                    "large": "https://cdn.intra.42.fr/users/ac4f1baa948c4a6b8357415e22a36067/large_rabounou.jpg",
                    "medium": "https://cdn.intra.42.fr/users/684c9ac2ebde961baa64d229ce32e31a/medium_rabounou.jpg",
                    "small": "https://cdn.intra.42.fr/users/330d172100907f3bcdde67842d4dddcc/small_rabounou.jpg",
                    "micro": "https://cdn.intra.42.fr/users/2aab925e024d5aa1bf83b8cca9c3d280/micro_rabounou.jpg"
                }
            },
            "staff?": false,
            "correction_point": 5,
            "pool_month": "june",
            "pool_year": "2024",
            "location": "e1r13p1",
            "wallet": 40,
            "anonymize_date": "2028-07-06T00:00:00.000+01:00",
            "data_erasure_date": "2028-07-06T00:00:00.000+01:00",
            "created_at": "2024-06-21T09:59:35.635Z",
            "updated_at": "2025-07-05T20:55:37.992Z",
            "alumnized_at": null,
            "alumni?": false,
            "active?": true
        }
    }
]